repository_core/__init__.py
repository_core/exceptions/__init__.py
repository_core/exceptions/exceptions.py
repository_core/models/__init__.py
repository_core/models/base_model.py
repository_core/repository/__init__.py
repository_core/repository/base_repository.py
repository_core/schemas/__init__.py
repository_core/schemas/base_schema.py
repository_core/services/__init__.py
repository_core/services/base_service.py
repository_core/utils/__init__.py
repository_core/utils/schema.py
repository_core-0.2.0.dist-info/METADATA
repository_core-0.2.0.dist-info/WHEEL
repository_core-0.2.0.dist-info/RECORD
